earthengine_api-1.6.11.dist-info/licenses/LICENSE
ee/__init__.py
ee/_arg_types.py
ee/_cloud_api_utils.py
ee/_helpers.py
ee/_utils.py
ee/apifunction.py
ee/apitestcase.py
ee/batch.py
ee/blob.py
ee/classifier.py
ee/clusterer.py
ee/collection.py
ee/computedobject.py
ee/confusionmatrix.py
ee/customfunction.py
ee/data.py
ee/daterange.py
ee/deprecation.py
ee/deserializer.py
ee/dictionary.py
ee/ee_array.py
ee/ee_date.py
ee/ee_exception.py
ee/ee_list.py
ee/ee_number.py
ee/ee_string.py
ee/ee_types.py
ee/element.py
ee/encodable.py
ee/errormargin.py
ee/feature.py
ee/featurecollection.py
ee/filter.py
ee/function.py
ee/geometry.py
ee/image.py
ee/image_converter.py
ee/imagecollection.py
ee/join.py
ee/kernel.py
ee/mapclient.py
ee/model.py
ee/oauth.py
ee/pixeltype.py
ee/projection.py
ee/py.typed
ee/reducer.py
ee/serializer.py
ee/table_converter.py
ee/terrain.py
ee/cli/__init__.py
ee/cli/commands.py
ee/cli/eecli.py
ee/cli/eecli_wrapper.py
ee/cli/utils.py
ee/tests/_cloud_api_utils_test.py
ee/tests/_helpers_test.py
ee/tests/_utils_test.py
ee/tests/algorithms.json
ee/tests/apifunction_test.py
ee/tests/batch_test.py
ee/tests/blob_test.py
ee/tests/classifier_test.py
ee/tests/cloud_api_discovery_document.json
ee/tests/clusterer_test.py
ee/tests/collection_test.py
ee/tests/computedobject_test.py
ee/tests/confusionmatrix_test.py
ee/tests/data_test.py
ee/tests/daterange_test.py
ee/tests/deprecation_test.py
ee/tests/deserializer_test.py
ee/tests/dictionary_test.py
ee/tests/ee_array_test.py
ee/tests/ee_date_test.py
ee/tests/ee_list_test.py
ee/tests/ee_number_test.py
ee/tests/ee_string_test.py
ee/tests/ee_test.py
ee/tests/ee_types_test.py
ee/tests/element_test.py
ee/tests/errormargin_test.py
ee/tests/feature_test.py
ee/tests/featurecollection_test.py
ee/tests/filter_test.py
ee/tests/function_test.py
ee/tests/geometry_point_test.py
ee/tests/geometry_test.py
ee/tests/image_converter_test.py
ee/tests/image_test.py
ee/tests/imagecollection_test.py
ee/tests/join_test.py
ee/tests/kernel_test.py
ee/tests/model_test.py
ee/tests/oauth_test.py
earthengine_api-1.6.11.dist-info/METADATA
earthengine_api-1.6.11.dist-info/WHEEL
earthengine_api-1.6.11.dist-info/entry_points.txt
earthengine_api-1.6.11.dist-info/top_level.txt
earthengine_api-1.6.11.dist-info/RECORD
